ardor_silverstone/__init__.py
ardor_silverstone/controller.py
ardor_silverstone/hid_adapter/__init__.py
ardor_silverstone/hid_adapter/hid_adapter.py
ardor_silverstone/hid_adapter/hid_detector.py
ardor_silverstone-0.1.1.dist-info/METADATA
ardor_silverstone-0.1.1.dist-info/WHEEL
ardor_silverstone-0.1.1.dist-info/RECORD
