Metadata-Version: 2.1
Name: ardor-silverstone
Version: 0.1.1
Summary: Ardor Silverstone PC racing wheel library
License: MIT
Author: Kirill Zhosul
Author-email: kirillzhosul@yandex.com
Requires-Python: >=3.12,<4.0
Classifier: License :: OSI Approved :: MIT License
Classifier: Programming Language :: Python :: 3
Classifier: Programming Language :: Python :: 3.12
Requires-Dist: hidapi (>=0.14.0,<0.15.0)
